deepfinder/__init__.py
deepfinder/inference.py
deepfinder/losses.py
deepfinder/models.py
deepfinder/training.py
deepfinder/utils/__init__.py
deepfinder/utils/common.py
deepfinder/utils/core.py
deepfinder/utils/dataloader.py
deepfinder/utils/eval.py
deepfinder/utils/objl.py
deepfinder/utils/params.py
deepfinder/utils/smap.py
tirfm_deepfinder-0.2.1.dist-info/LICENSE
tirfm_deepfinder-0.2.1.dist-info/METADATA
tirfm_deepfinder-0.2.1.dist-info/WHEEL
tirfm_deepfinder-0.2.1.dist-info/entry_points.txt
tirfm_deepfinder-0.2.1.dist-info/top_level.txt
tirfm_deepfinder-0.2.1.dist-info/RECORD
