Metadata-Version: 2.1
Name: tirfm-deepfinder
Version: 0.2.1
Summary: ExoDeepFinder is an original deep learning approach to localize macromolecules in cryo electron tomography images. The method is based on image segmentation using a 3D convolutional neural network.
Author: E. Moebel
Author-email: emmanuel.moebel@gmail.com
License: GPL-3.0
Classifier: Development Status :: 4 - Beta
Classifier: Intended Audience :: Developers
Classifier: Intended Audience :: Science/Research
Classifier: Topic :: Scientific/Engineering
Classifier: Topic :: Scientific/Engineering :: Visualization
Classifier: Topic :: Scientific/Engineering :: Information Analysis
Classifier: Topic :: Scientific/Engineering :: Bio-Informatics
Classifier: Topic :: Scientific/Engineering :: Artificial Intelligence
Classifier: Topic :: Scientific/Engineering :: Image Processing
Classifier: Programming Language :: Python
Classifier: Programming Language :: Python :: 3
Classifier: Programming Language :: Python :: 3.8
Classifier: Programming Language :: Python :: 3.9
Classifier: Operating System :: OS Independent
Classifier: License :: OSI Approved :: GNU General Public License v3 (GPLv3)
Requires-Python: >=3.9
License-File: LICENSE
Requires-Dist: tensorflow ==2.11.1
Requires-Dist: lxml >=4.9.3
Requires-Dist: mrcfile >=1.4.3
Requires-Dist: scikit-learn ==1.3.2
Requires-Dist: scikit-image ==0.22.0
Requires-Dist: matplotlib >=3.8.1
Requires-Dist: PyQt5 ==5.13.2
Requires-Dist: pyqtgraph ==0.13.3
Requires-Dist: openpyxl >=3.1.2
Requires-Dist: pycm >=4.0
